{
    "took": 1,
    "timed_out": false,
    "_shards": {
        "total": 5,
        "successful": 5,
        "failed": 0
    },
    "hits": {
        "total": 1,
        "max_score": 2.4865634,
        "hits": [
            {
                "_index": "annotator",
                "_type": "annotation",
                "_id": "1636726307772",
                "_score": 2.4865634,
                "_source": {
                    "section_title": null,
                    "ranges": [
                        {
                            "endOffset": 529,
                            "startOffset": 512,
                            "start": "/div[1]/form[1]/div[7]/section[1]/div[1]/div[1]/div[9]/table[1]/tbody[1]/tr[1]/td[1]/div[1]/div[2]/div[2]",
                            "end": "/div[1]/form[1]/div[7]/section[1]/div[1]/div[1]/div[9]/table[1]/tbody[1]/tr[1]/td[1]/div[1]/div[2]/div[2]"
                        }
                    ],
                    "created": "2021-11-12T14:11:47.695670+00:00",
                    "section": null,
                    "uri": "https://latvija.lv/ppk/dzives-situacija/apakssituacija/p5551/procesaapraksts",
                    "quote": "šana, ceļa noklāš",
                    "statechanges": {},
                    "permissions": {
                        "read": [
                            "d.silva@deusto.es"
                        ],
                        "update": [
                            "d.silva@deusto.es"
                        ],
                        "admin": [
                            "d.silva@deusto.es"
                        ],
                        "delete": [
                            "d.silva@deusto.es"
                        ]
                    },
                    "data_creacio": 1636726292543,
                    "idAnotationReply": "annotation-1636726292600",
                    "text": "<p>this is the reply of the quesition</p>",
                    "state": 0,
                    "category": "reply",
                    "user": "d.silva@deusto.es",
                    "updated": "2021-11-12T14:11:47.695670+00:00",
                    "consumer": "***REMOVED***",
                    "order": "uxDescriptionLongPanel"
                }
            }
        ]
    }
}